equinix_metal/__init__.py
equinix_metal/api_client.py
equinix_metal/api_response.py
equinix_metal/configuration.py
equinix_metal/exceptions.py
equinix_metal/py.typed
equinix_metal/rest.py
equinix_metal/api/__init__.py
equinix_metal/api/authentication_api.py
equinix_metal/api/batches_api.py
equinix_metal/api/bgp_api.py
equinix_metal/api/capacity_api.py
equinix_metal/api/console_log_details_api.py
equinix_metal/api/devices_api.py
equinix_metal/api/emails_api.py
equinix_metal/api/events_api.py
equinix_metal/api/facilities_api.py
equinix_metal/api/firmware_sets_api.py
equinix_metal/api/hardware_reservations_api.py
equinix_metal/api/incidents_api.py
equinix_metal/api/interconnections_api.py
equinix_metal/api/invitations_api.py
equinix_metal/api/invoices_api.py
equinix_metal/api/ip_addresses_api.py
equinix_metal/api/licenses_api.py
equinix_metal/api/memberships_api.py
equinix_metal/api/metal_gateways_api.py
equinix_metal/api/metros_api.py
equinix_metal/api/operating_systems_api.py
equinix_metal/api/organizations_api.py
equinix_metal/api/otps_api.py
equinix_metal/api/password_reset_tokens_api.py
equinix_metal/api/payment_methods_api.py
equinix_metal/api/plans_api.py
equinix_metal/api/ports_api.py
equinix_metal/api/projects_api.py
equinix_metal/api/self_service_reservations_api.py
equinix_metal/api/spot_market_api.py
equinix_metal/api/ssh_keys_api.py
equinix_metal/api/support_request_api.py
equinix_metal/api/transfer_requests_api.py
equinix_metal/api/two_factor_auth_api.py
equinix_metal/api/usages_api.py
equinix_metal/api/user_verification_tokens_api.py
equinix_metal/api/userdata_api.py
equinix_metal/api/users_api.py
equinix_metal/api/vlans_api.py
equinix_metal/api/vrfs_api.py
equinix_metal/models/__init__.py
equinix_metal/models/activate_hardware_reservation_request.py
equinix_metal/models/address.py
equinix_metal/models/attribute.py
equinix_metal/models/attribute_data.py
equinix_metal/models/auth_token.py
equinix_metal/models/auth_token_input.py
equinix_metal-0.11.0.dist-info/METADATA
equinix_metal-0.11.0.dist-info/WHEEL
equinix_metal-0.11.0.dist-info/top_level.txt
equinix_metal-0.11.0.dist-info/RECORD
