Metadata-Version: 2.1
Name: equinix-metal
Version: 0.11.0
Summary: Metal API
Home-page: 
Author: Equinix Metal API Team
Author-email: support@equinixmetal.com
License: Equinix Metal
Keywords: OpenAPI,OpenAPI-Generator,Metal API
Requires-Dist: urllib3 <2.1.0,>=1.25.3
Requires-Dist: python-dateutil
Requires-Dist: pydantic >=2
Requires-Dist: typing-extensions >=4.7.1
